tendril/__init__.py
tendril/config/__init__.py
tendril/config/geda.py
tendril/connectors/__init__.py
tendril/connectors/geda/__init__.py
tendril/connectors/geda/gschem.py
tendril/connectors/geda/pcb.py
tendril/connectors/geda/projfile.py
tendril/entities/__init__.py
tendril/entities/edasymbols/__init__.py
tendril/entities/edasymbols/geda.py
tendril/entities/projects/__init__.py
tendril/entities/projects/geda.py
tendril/libraries/__init__.py
tendril/libraries/edasymbols/__init__.py
tendril/libraries/edasymbols/geda.py
tendril/schema/__init__.py
tendril/schema/gedaprojects.py
tendril/schema/gedasymbols.py
tendril_connector_geda-0.1.2.dist-info/LICENSE
tendril_connector_geda-0.1.2.dist-info/METADATA
tendril_connector_geda-0.1.2.dist-info/WHEEL
tendril_connector_geda-0.1.2.dist-info/entry_points.txt
tendril_connector_geda-0.1.2.dist-info/top_level.txt
tendril_connector_geda-0.1.2.dist-info/RECORD
