Metadata-Version: 2.1
Name: tendril-connector-geda
Version: 0.1.2
Summary: gEDA connector for tendril
Home-page: https://github.com/tendril-framework/tendril-connector-geda
Author: Chintalagiri Shashank
Author-email: shashank@chintal.in
License: UNKNOWN
Project-URL: Source Repository, https://github.com/tendril-framework/tendril-eda
Project-URL: Bug Tracker, https://github.com/tendril-framework/tendril-eda/issues
Project-URL: Documentation, https://tendril-eda.readthedocs.io/en/latest
Keywords: tendril
Platform: any
Classifier: Development Status :: 4 - Beta
Classifier: License :: OSI Approved :: GNU Affero General Public License v3 or later (AGPLv3+)
Classifier: Natural Language :: English
Classifier: Operating System :: OS Independent
Classifier: Programming Language :: Python
Classifier: Programming Language :: Python :: 2.7
Classifier: Programming Language :: Python :: 3
Classifier: Programming Language :: Python :: 3.5
Classifier: Programming Language :: Python :: 3.6
Classifier: Programming Language :: Python :: 3.7
Classifier: Programming Language :: Python :: Implementation :: CPython
Classifier: Programming Language :: Python :: Implementation :: PyPy
Requires-Python: >=2.7, !=3.0.*, !=3.1.*, !=3.2.*, !=3.3.*
Requires-Dist: arrow
Requires-Dist: tendril-eda
Requires-Dist: tendril-config
Requires-Dist: tendril-identity
Requires-Dist: tendril-utils-core
Requires-Dist: tendril-utils-types
Requires-Dist: tendril-utils-vcs
Requires-Dist: tendril-utils-pdf
Requires-Dist: tendril-utils-gschem-files
Requires-Dist: tendril-conventions-electronics
Requires-Dist: wheel
Provides-Extra: build
Requires-Dist: setuptools-scm ; extra == 'build'
Requires-Dist: sphinx ; extra == 'build'
Requires-Dist: sphinx-argparse ; extra == 'build'
Requires-Dist: alabaster ; extra == 'build'
Requires-Dist: pytest ; extra == 'build'
Requires-Dist: pytest-flake8 ; extra == 'build'
Requires-Dist: pytest-cov ; extra == 'build'
Requires-Dist: coveralls[yaml] ; extra == 'build'
Provides-Extra: dev
Requires-Dist: setuptools-scm ; extra == 'dev'
Requires-Dist: sphinx ; extra == 'dev'
Requires-Dist: sphinx-argparse ; extra == 'dev'
Requires-Dist: alabaster ; extra == 'dev'
Requires-Dist: pytest ; extra == 'dev'
Requires-Dist: pytest-flake8 ; extra == 'dev'
Requires-Dist: pytest-cov ; extra == 'dev'
Requires-Dist: coveralls[yaml] ; extra == 'dev'
Provides-Extra: docs
Requires-Dist: setuptools-scm ; extra == 'docs'
Requires-Dist: sphinx ; extra == 'docs'
Requires-Dist: sphinx-argparse ; extra == 'docs'
Requires-Dist: alabaster ; extra == 'docs'
Provides-Extra: publish
Requires-Dist: setuptools-scm ; extra == 'publish'
Requires-Dist: sphinx ; extra == 'publish'
Requires-Dist: sphinx-argparse ; extra == 'publish'
Requires-Dist: alabaster ; extra == 'publish'
Requires-Dist: pytest ; extra == 'publish'
Requires-Dist: pytest-flake8 ; extra == 'publish'
Requires-Dist: pytest-cov ; extra == 'publish'
Requires-Dist: coveralls[yaml] ; extra == 'publish'
Requires-Dist: twine ; extra == 'publish'
Requires-Dist: pygithub ; extra == 'publish'
Provides-Extra: tests
Requires-Dist: setuptools-scm ; extra == 'tests'
Requires-Dist: sphinx ; extra == 'tests'
Requires-Dist: sphinx-argparse ; extra == 'tests'
Requires-Dist: alabaster ; extra == 'tests'
Requires-Dist: pytest ; extra == 'tests'
Requires-Dist: pytest-flake8 ; extra == 'tests'
Requires-Dist: pytest-cov ; extra == 'tests'
Requires-Dist: coveralls[yaml] ; extra == 'tests'
